{"en-us_develop_about.md":"DtjiawdV","en-us_develop_api.md":"D72gKAbI","en-us_guide_configuration.md":"DJhuZEcY","en-us_guide_faq.md":"qJ6j7zjt","en-us_guide_getting-started.md":"CqwqkVx5","en-us_guide_voice.md":"DnOoivB0","en-us_index.md":"C3BN4QhM","index.md":"DoyjF9P5","zh-cn_develop_about.md":"Cg7QqEZ9","zh-cn_develop_api.md":"azj3P_Qu","zh-cn_develop_event.md":"CVroChY5","zh-cn_develop_extends_api.md":"ef7_QtCl","zh-cn_develop_msg.md":"BZOWGnrZ","zh-cn_develop_quick-start.md":"CSGIjUAz","zh-cn_guide_configuration.md":"DQvMrz-m","zh-cn_guide_faq.md":"Dc9qB15A","zh-cn_guide_ffmpeg.md":"CBPD8A-9","zh-cn_guide_getting-started.md":"Dz3qTbMI","zh-cn_guide_nonebot2.md":"B5Gs3P2m","zh-cn_index.md":"BWQcEf2z"}
